services/__init__.py
services/algservice/__init__.py
services/algservice/alg_service.py
services/algservice/alg_service_api.py
services/algservice/grpcutils.py
services/algservice/models.py
services/algservice/pb2utils.py
services/grpc/__init__.py
services/grpc/alg_service_pb2.py
services/grpc/alg_service_pb2.pyi
services/grpc/alg_service_pb2_grpc.py
tools/__init__.py
util/__init__.py
util/exceptions.py
util/jsonencoder.py
util/syncutils.py
util/utils.py
alg_service_p12_api-1.0.2.dist-info/METADATA
alg_service_p12_api-1.0.2.dist-info/WHEEL
alg_service_p12_api-1.0.2.dist-info/top_level.txt
alg_service_p12_api-1.0.2.dist-info/RECORD
